scrapy_link_filter/__init__.py
scrapy_link_filter/__version__.py
scrapy_link_filter/middleware.py
test/__init__.py
test/test_mw.py
scrapy_link_filter-0.2.0.dist-info/LICENSE
scrapy_link_filter-0.2.0.dist-info/METADATA
scrapy_link_filter-0.2.0.dist-info/WHEEL
scrapy_link_filter-0.2.0.dist-info/top_level.txt
scrapy_link_filter-0.2.0.dist-info/RECORD
