Metadata-Version: 2.1
Name: scrapy-link-filter
Version: 0.2.0
Summary: Scrapy Middleware that allows a Scrapy Spider to filter requests.
Home-page: https://github.com/croqaz/scrapy-link-filter
Author: Cristi Constantin
Author-email: cristi.constantin@speedpost.net
License: BSD
Keywords: scrapy link filter
Platform: Any
Classifier: Development Status :: 4 - Beta
Classifier: Environment :: Console
Classifier: Intended Audience :: Developers
Classifier: Natural Language :: English
Classifier: Operating System :: OS Independent
Classifier: License :: OSI Approved :: BSD License
Classifier: Programming Language :: Python :: 3 :: Only
Classifier: Programming Language :: Python :: 3.6
Classifier: Programming Language :: Python :: 3.7
Classifier: Topic :: Software Development
Classifier: Framework :: Scrapy
Requires-Python: >=3.6.0
